[
  {
    "ContainingType": "Seek.API.Controllers.Database_Existence_CheckerController",
    "Method": "CheckDatabase",
    "RelativePath": "api/Database_Existence_Checker/check",
    "HttpMethod": "GET",
    "IsController": true,
    "Order": 0,
    "Parameters": [
      {
        "Name": "api-version",
        "Type": "System.String",
        "IsRequired": false
      }
    ],
    "ReturnTypes": []
  },
  {
    "ContainingType": "Seek.API.Controllers.DatabaseSecurityController",
    "Method": "Decrypt",
    "RelativePath": "api/DatabaseSecurity/Decrypt",
    "HttpMethod": "POST",
    "IsController": true,
    "Order": 0,
    "Parameters": [
      {
        "Name": "request",
        "Type": "Seek.Core.Helper_Classes.TransformRequest",
        "IsRequired": true
      },
      {
        "Name": "api-version",
        "Type": "System.String",
        "IsRequired": false
      }
    ],
    "ReturnTypes": []
  },
  {
    "ContainingType": "Seek.API.Controllers.DatabaseSecurityController",
    "Method": "Encrypt",
    "RelativePath": "api/DatabaseSecurity/Encrypt",
    "HttpMethod": "POST",
    "IsController": true,
    "Order": 0,
    "Parameters": [
      {
        "Name": "databasePath",
        "Type": "System.String",
        "IsRequired": false
      },
      {
        "Name": "api-version",
        "Type": "System.String",
        "IsRequired": false
      }
    ],
    "ReturnTypes": []
  }
]